tellie.py
Tellie-2.1.9.dist-info/METADATA
Tellie-2.1.9.dist-info/WHEEL
Tellie-2.1.9.dist-info/entry_points.txt
Tellie-2.1.9.dist-info/top_level.txt
Tellie-2.1.9.dist-info/RECORD
